{"id":"L2TH2CNY7ZQWL","name":"@ayezakhan.ak","size":118295,"btime":1651783192995,"mtime":1651783192995,"ext":"jpg","tags":[],"folders":[],"isDeleted":false,"url":"https://www.instagram.com/p/CdLpr3ytou_/","annotation":"","modificationTime":1651783192990,"noThumbnail":true,"width":1440,"height":1440,"lastModified":1651783193283,"palettes":[{"color":[238,229,231],"ratio":52},{"color":[33,28,29],"ratio":33},{"color":[194,152,135],"ratio":3.56},{"color":[90,73,70],"ratio":3.11},{"color":[154,107,89],"ratio":2.73},{"color":[191,182,178],"ratio":2.36},{"color":[158,147,142],"ratio":1.44},{"color":[198,173,160],"ratio":1.13}]}