{"id":"L0NUAIKU9E20Y","name":"Pure Inspiration A roundup of Inbox UI, Holidays and more","size":438611,"btime":1647089047190,"mtime":1647089047191,"ext":"png","tags":[],"folders":[],"isDeleted":false,"url":"https://dribbble.com/shots/5708399-Christmas-Collisions","annotation":"","modificationTime":1647089047182,"height":1200,"width":1600,"lastModified":1647089047491,"palettes":[{"color":[27,27,28],"ratio":49},{"color":[242,240,243],"ratio":43},{"color":[250,200,196],"ratio":2.75},{"color":[249,186,174],"ratio":1.65},{"color":[238,159,150],"ratio":1.48},{"color":[133,136,140],"ratio":0.79},{"color":[181,97,91],"ratio":0.41},{"color":[238,135,121],"ratio":0.4}]}