{"id":"KZISSPKUFD9C9","name":"AT 3 — 3D, Graphic Design  Typography","size":269338,"btime":1644607423619,"mtime":1644607423620,"ext":"jpg","tags":[],"folders":[],"isDeleted":false,"url":"https://abduzeedo.com/3-3d-graphic-design-typography","annotation":"","modificationTime":1644607423614,"height":1600,"width":1030,"lastModified":1644607423906,"palettes":[{"color":[7,7,7],"ratio":84},{"color":[171,171,171],"ratio":4.25},{"color":[87,87,87],"ratio":4.2},{"color":[39,39,39],"ratio":2.11},{"color":[28,28,28],"ratio":1.62},{"color":[52,52,52],"ratio":0.81},{"color":[60,60,60],"ratio":0.72},{"color":[116,116,116],"ratio":0.56},{"color":[140,140,140],"ratio":0.54},{"color":[124,124,124],"ratio":0.5},{"color":[132,132,132],"ratio":0.43}]}