{"id":"KZXDPRRU47PW3","name":"Lettering Inspiration by Rafael Serra","size":41278,"btime":1645489084894,"mtime":1645489084894,"ext":"png","tags":[],"folders":[],"isDeleted":false,"url":"https://abduzeedo.com/lettering-inspiration-rafael-serra","annotation":"","modificationTime":1645489084890,"noThumbnail":true,"width":1200,"height":1200,"lastModified":1645489085157,"palettes":[{"color":[28,28,28],"ratio":93},{"color":[232,232,218],"ratio":3.82},{"color":[15,174,134],"ratio":0.75},{"color":[115,114,107],"ratio":0.63},{"color":[66,63,61],"ratio":0.49},{"color":[247,67,43],"ratio":0.35}]}