{"id":"L33IY1T760857","name":"by YeJun Lee","size":534708,"btime":1652391013300,"mtime":1652391013300,"ext":"jpg","tags":[],"folders":[],"isDeleted":false,"url":"https://www.artstation.com/artwork/RnN1ae","annotation":"","modificationTime":1652391013291,"height":2048,"width":1517,"lastModified":1652391013618,"palettes":[{"color":[125,142,152],"ratio":58},{"color":[34,33,35],"ratio":21},{"color":[205,193,180],"ratio":9},{"color":[127,110,97],"ratio":4.08},{"color":[74,79,87],"ratio":3.43},{"color":[90,73,61],"ratio":2.18},{"color":[100,89,86],"ratio":1.12}]}