{"id":"KZISNQ63JAZJI","name":"Branding and Design Guidelines for Atmovum","size":137418,"btime":1644607191102,"mtime":1644607191102,"ext":"jpg","tags":[],"folders":[],"isDeleted":false,"url":"https://abduzeedo.com/index.php/branding-and-design-guidelines-atmovum","annotation":"","modificationTime":1644607191099,"noThumbnail":true,"width":1400,"height":897,"lastModified":1644607191355,"palettes":[{"color":[232,232,232],"ratio":49},{"color":[32,32,32],"ratio":21},{"color":[132,133,133],"ratio":11},{"color":[37,186,172],"ratio":9},{"color":[171,172,171],"ratio":4},{"color":[94,94,94],"ratio":1.73},{"color":[156,156,155],"ratio":0.88},{"color":[57,108,85],"ratio":0.48}]}