{"id":"L1PTSITC39U8G","name":"PSYwJ3BM7S9TSTUDEj2zLjljmo~PkER2g_WAOV3s1b7mTi2-AvuTNeXDZZ2ycXh6BRNiBE","size":305025,"btime":1649385922376,"mtime":1649385922376,"ext":"gif","tags":[],"folders":[],"isDeleted":false,"url":"https://iconscout.com/lottie/praying-woman-514330","annotation":"","modificationTime":1649385922368,"height":512,"width":512,"lastModified":1649385923200,"palettes":[{"color":[251,251,251],"ratio":63},{"color":[140,147,167],"ratio":20},{"color":[40,40,69],"ratio":12},{"color":[246,214,171],"ratio":1.74},{"color":[118,120,139],"ratio":0.71},{"color":[106,104,113],"ratio":0.47}]}